dbos_mcp/__init__.py
dbos_mcp/client.py
dbos_mcp/server.py
dbos_mcp-0.2.1.dist-info/METADATA
dbos_mcp-0.2.1.dist-info/WHEEL
dbos_mcp-0.2.1.dist-info/entry_points.txt
dbos_mcp-0.2.1.dist-info/licenses/LICENSE
dbos_mcp-0.2.1.dist-info/RECORD
