Metadata-Version: 2.4
Name: dbos-mcp
Version: 0.2.1
Summary: MCP server for DBOS Conductor workflow introspection and management
Project-URL: Homepage, https://github.com/dbos-inc/dbos-mcp
Project-URL: Repository, https://github.com/dbos-inc/dbos-mcp
Author: DBOS, Inc.
License: MIT
License-File: LICENSE
Keywords: claude,conductor,dbos,mcp,workflow
Classifier: Development Status :: 4 - Beta
Classifier: License :: OSI Approved :: MIT License
Classifier: Programming Language :: Python :: 3.10
Classifier: Programming Language :: Python :: 3.11
Classifier: Programming Language :: Python :: 3.12
Classifier: Programming Language :: Python :: 3.13
Requires-Python: >=3.10
Requires-Dist: httpx>=0.27.0
Requires-Dist: mcp[cli]>=1.25.0
